{
"timestamp": "Thu Nov 13 16:05:20 2014",
"org_type": "school",
"org_name": "",
"org_code": "0184",
"exhibit": {
	"id": "mgp_scores",
	"data":  
[{"key":{"year":2013,"subgroup":"All","subject":"Math"},"val":{"mgp_1yr":"32","mgp_2yr":null}},{"key":{"year":2013,"subgroup":"All","subject":"Reading"},"val":{"mgp_1yr":"37","mgp_2yr":null}},{"key":{"year":2013,"subgroup":"Economy","subject":"Math"},"val":{"mgp_1yr":"23","mgp_2yr":"33"}},{"key":{"year":2013,"subgroup":"Economy","subject":"Reading"},"val":{"mgp_1yr":"28","mgp_2yr":"30"}},{"key":{"year":2014,"subgroup":"All","subject":"Math"},"val":{"mgp_1yr":"57","mgp_2yr":"45"}},{"key":{"year":2014,"subgroup":"All","subject":"Reading"},"val":{"mgp_1yr":"59","mgp_2yr":"48.3"}},{"key":{"year":2014,"subgroup":"Economy","subject":"Math"},"val":{"mgp_1yr":"55","mgp_2yr":null}},{"key":{"year":2014,"subgroup":"Economy","subject":"Reading"},"val":{"mgp_1yr":"52","mgp_2yr":null}},{"key":{"year":2014,"subgroup":"FEMALE","subject":"Math"},"val":{"mgp_1yr":"56","mgp_2yr":null}},{"key":{"year":2014,"subgroup":"FEMALE","subject":"Reading"},"val":{"mgp_1yr":"66.5","mgp_2yr":null}},{"key":{"year":2014,"subgroup":"LEP","subject":"Math"},"val":{"mgp_1yr":"54.5","mgp_2yr":null}},{"key":{"year":2014,"subgroup":"LEP","subject":"Reading"},"val":{"mgp_1yr":"48.5","mgp_2yr":null}},{"key":{"year":2014,"subgroup":"SPED","subject":"Math"},"val":{"mgp_1yr":"95","mgp_2yr":null}},{"key":{"year":2014,"subgroup":"SPED","subject":"Reading"},"val":{"mgp_1yr":"32.5","mgp_2yr":null}},{"key":{"year":2014,"subgroup":"WH7","subject":"Math"},"val":{"mgp_1yr":"13","mgp_2yr":null}},{"key":{"year":2014,"subgroup":"WH7","subject":"Reading"},"val":{"mgp_1yr":"86","mgp_2yr":null}}]
	}
}
