{
"timestamp": "Wed Oct 14 15:44:58 2015",
"org_type": "school",
"org_name": "",
"org_code": "0170",
"exhibit": {
	"id": "suspensions",
	"data":  
[
    {
        "key": {
            "school_code": "0170",
            "subgroup": "All"
        },
        "val": {
            "state_suspended_1": 0.2156,
            "suspended_1": 0.266,
            "state_suspended_11": 0.0008,
            "suspended_11": 0.0027,
            "incidents": 227
        }
    },
    {
        "key": {
            "school_code": "0170",
            "subgroup": "AM7"
        },
        "val": {
            "state_suspended_1": 0.0732,
            "suspended_1": 0.0682,
            "state_suspended_11": 0,
            "suspended_11": 0,
            "incidents": null
        }
    },
    {
        "key": {
            "school_code": "0170",
            "subgroup": "BL7"
        },
        "val": {
            "state_suspended_1": 0.268,
            "suspended_1": 0.2931,
            "state_suspended_11": 0.0011,
            "suspended_11": 0.003,
            "incidents": null
        }
    },
    {
        "key": {
            "school_code": "0170",
            "subgroup": "Economy"
        },
        "val": {
            "state_suspended_1": 0.2621,
            "suspended_1": 0.3813,
            "state_suspended_11": 0.001,
            "suspended_11": 0,
            "incidents": null
        }
    },
    {
        "key": {
            "school_code": "0170",
            "subgroup": "FEMALE"
        },
        "val": {
            "state_suspended_1": 0.1802,
            "suspended_1": 0.2303,
            "state_suspended_11": 0.0007,
            "suspended_11": 0.0056,
            "incidents": null
        }
    },
    {
        "key": {
            "school_code": "0170",
            "subgroup": "LEP"
        },
        "val": {
            "state_suspended_1": 0.1055,
            "suspended_1": 0.0833,
            "state_suspended_11": 0,
            "suspended_11": 0,
            "incidents": null
        }
    },
    {
        "key": {
            "school_code": "0170",
            "subgroup": "MALE"
        },
        "val": {
            "state_suspended_1": 0.2504,
            "suspended_1": 0.298,
            "state_suspended_11": 0.0009,
            "suspended_11": 0,
            "incidents": null
        }
    },
    {
        "key": {
            "school_code": "0170",
            "subgroup": "SPED"
        },
        "val": {
            "state_suspended_1": 0.3047,
            "suspended_1": 0.4038,
            "state_suspended_11": 0.0004,
            "suspended_11": 0,
            "incidents": null
        }
    }
]

	}
}
