{
"timestamp": "Wed Nov 18 12:46:12 2015",
"org_type": "school",
"org_name": "",
"org_code": "0450",
"exhibit": {
	"id": "suspensions",
	"data":  
[
    {
        "key": {
            "year": 2015,
            "subgroup": "All"
        },
        "val": {
            "suspended_1": 0.31,
            "suspended_11": 0.0121,
            "state_suspended_1": 0.156,
            "state_suspended_11": 0.0076,
            "incidents": 405
        }
    },
    {
        "key": {
            "year": 2015,
            "subgroup": "BL7"
        },
        "val": {
            "suspended_1": 0.308,
            "suspended_11": 0.0121,
            "state_suspended_1": 0.185,
            "state_suspended_11": 0.0093,
            "incidents": 0
        }
    },
    {
        "key": {
            "year": 2015,
            "subgroup": "Economy"
        },
        "val": {
            "suspended_1": 0.31,
            "suspended_11": 0.0121,
            "state_suspended_1": 0.184,
            "state_suspended_11": 0.0094,
            "incidents": 0
        }
    },
    {
        "key": {
            "year": 2015,
            "subgroup": "FEMALE"
        },
        "val": {
            "suspended_1": 0.248,
            "suspended_11": 0.0062,
            "state_suspended_1": 0.13,
            "state_suspended_11": 0.0045,
            "incidents": 0
        }
    },
    {
        "key": {
            "year": 2015,
            "subgroup": "MALE"
        },
        "val": {
            "suspended_1": 0.37,
            "suspended_11": 0.0178,
            "state_suspended_1": 0.183,
            "state_suspended_11": 0.0108,
            "incidents": 0
        }
    },
    {
        "key": {
            "year": 2015,
            "subgroup": "SPED"
        },
        "val": {
            "suspended_1": 0.432,
            "suspended_11": 0.0162,
            "state_suspended_1": 0.279,
            "state_suspended_11": 0.0148,
            "incidents": 0
        }
    }
]

	}
}
