{
"timestamp": "Wed Oct 29 10:00:16 2014
",
"org_type": "lea",
"org_name": "CAPITAL CITY PCS",
"org_code": "0108",
"exhibit": {
	"id": "graduation",
	"data":  
[{"key":{"subgroup":"All","year":2014},"val":{"graduates":51,"cohort_size":79}},{"key":{"subgroup":"MALE","year":2014},"val":{"graduates":19,"cohort_size":33}},{"key":{"subgroup":"FEMALE","year":2014},"val":{"graduates":32,"cohort_size":46}},{"key":{"subgroup":"HI7","year":2014},"val":{"graduates":33,"cohort_size":48}},{"key":{"subgroup":"Economy","year":2014},"val":{"graduates":38,"cohort_size":59}},{"key":{"subgroup":"All","year":2012},"val":{"graduates":41,"cohort_size":55}},{"key":{"subgroup":"FEMALE","year":2012},"val":{"graduates":26,"cohort_size":32}},{"key":{"subgroup":"HI7","year":2012},"val":{"graduates":22,"cohort_size":27}},{"key":{"subgroup":"Economy","year":2012},"val":{"graduates":30,"cohort_size":39}},{"key":{"subgroup":"All","year":2013},"val":{"graduates":48,"cohort_size":61}},{"key":{"subgroup":"MALE","year":2013},"val":{"graduates":21,"cohort_size":28}},{"key":{"subgroup":"FEMALE","year":2013},"val":{"graduates":27,"cohort_size":33}},{"key":{"subgroup":"BL7","year":2013},"val":{"graduates":25,"cohort_size":31}},{"key":{"subgroup":"HI7","year":2013},"val":{"graduates":20,"cohort_size":27}},{"key":{"subgroup":"Economy","year":2013},"val":{"graduates":35,"cohort_size":40}}]
	}
}
