{
"timestamp": "Mon Nov 06 16:55:03 2017",
"org_type": "school",
"org_name": "LUKE MOORE ALTERNATIVE HS",
"org_code": "0884",
"exhibit": {
	"id": "graduation",
	"data":  
[
    {
        "key": {
            "subgroup": "Economy",
            "year": 2016,
            "type": "Four Year ACGR"
        },
        "val": {
            "acgr": 0.375,
            "suppressed": 0
        }
    },
    {
        "key": {
            "subgroup": "All",
            "year": 2011,
            "type": "Four Year ACGR"
        },
        "val": {
            "acgr": 0.241,
            "suppressed": 0
        }
    },
    {
        "key": {
            "subgroup": "MALE",
            "year": 2011,
            "type": "Four Year ACGR"
        },
        "val": {
            "acgr": 0.211,
            "suppressed": 0
        }
    },
    {
        "key": {
            "subgroup": "FEMALE",
            "year": 2011,
            "type": "Four Year ACGR"
        },
        "val": {
            "acgr": 0.281,
            "suppressed": 0
        }
    },
    {
        "key": {
            "subgroup": "BL7",
            "year": 2011,
            "type": "Four Year ACGR"
        },
        "val": {
            "acgr": 0.246,
            "suppressed": 0
        }
    },
    {
        "key": {
            "subgroup": "Economy",
            "year": 2011,
            "type": "Four Year ACGR"
        },
        "val": {
            "acgr": 0.293,
            "suppressed": 0
        }
    },
    {
        "key": {
            "subgroup": "All",
            "year": 2012,
            "type": "Four Year ACGR"
        },
        "val": {
            "acgr": 0.356,
            "suppressed": 0
        }
    },
    {
        "key": {
            "subgroup": "MALE",
            "year": 2012,
            "type": "Four Year ACGR"
        },
        "val": {
            "acgr": 0.289,
            "suppressed": 0
        }
    },
    {
        "key": {
            "subgroup": "FEMALE",
            "year": 2012,
            "type": "Four Year ACGR"
        },
        "val": {
            "acgr": 0.414,
            "suppressed": 0
        }
    },
    {
        "key": {
            "subgroup": "BL7",
            "year": 2012,
            "type": "Four Year ACGR"
        },
        "val": {
            "acgr": 0.365,
            "suppressed": 0
        }
    },
    {
        "key": {
            "subgroup": "Economy",
            "year": 2012,
            "type": "Four Year ACGR"
        },
        "val": {
            "acgr": 0.355,
            "suppressed": 0
        }
    },
    {
        "key": {
            "subgroup": "All",
            "year": 2013,
            "type": "Four Year ACGR"
        },
        "val": {
            "acgr": 0.413,
            "suppressed": 0
        }
    },
    {
        "key": {
            "subgroup": "MALE",
            "year": 2013,
            "type": "Four Year ACGR"
        },
        "val": {
            "acgr": 0.358,
            "suppressed": 0
        }
    },
    {
        "key": {
            "subgroup": "FEMALE",
            "year": 2013,
            "type": "Four Year ACGR"
        },
        "val": {
            "acgr": 0.455,
            "suppressed": 0
        }
    },
    {
        "key": {
            "subgroup": "BL7",
            "year": 2013,
            "type": "Four Year ACGR"
        },
        "val": {
            "acgr": 0.412,
            "suppressed": 0
        }
    },
    {
        "key": {
            "subgroup": "Economy",
            "year": 2013,
            "type": "Four Year ACGR"
        },
        "val": {
            "acgr": 0.413,
            "suppressed": 0
        }
    },
    {
        "key": {
            "subgroup": "All",
            "year": 2015,
            "type": "Four Year ACGR"
        },
        "val": {
            "acgr": 0.399,
            "suppressed": 0
        }
    },
    {
        "key": {
            "subgroup": "BL7",
            "year": 2015,
            "type": "Four Year ACGR"
        },
        "val": {
            "acgr": 0.38,
            "suppressed": 0
        }
    },
    {
        "key": {
            "subgroup": "Economy",
            "year": 2015,
            "type": "Four Year ACGR"
        },
        "val": {
            "acgr": 0.404,
            "suppressed": 0
        }
    },
    {
        "key": {
            "subgroup": "FEMALE",
            "year": 2015,
            "type": "Four Year ACGR"
        },
        "val": {
            "acgr": 0.508,
            "suppressed": 0
        }
    },
    {
        "key": {
            "subgroup": "MALE",
            "year": 2015,
            "type": "Four Year ACGR"
        },
        "val": {
            "acgr": 0.312,
            "suppressed": 0
        }
    },
    {
        "key": {
            "subgroup": "All",
            "year": 2016,
            "type": "Five Year ACGR"
        },
        "val": {
            "acgr": 0.514,
            "suppressed": 0
        }
    },
    {
        "key": {
            "subgroup": "BL7",
            "year": 2016,
            "type": "Five Year ACGR"
        },
        "val": {
            "acgr": 0.496,
            "suppressed": 0
        }
    },
    {
        "key": {
            "subgroup": "Economy",
            "year": 2016,
            "type": "Five Year ACGR"
        },
        "val": {
            "acgr": 0.522,
            "suppressed": 0
        }
    },
    {
        "key": {
            "subgroup": "FEMALE",
            "year": 2016,
            "type": "Five Year ACGR"
        },
        "val": {
            "acgr": 0.639,
            "suppressed": 0
        }
    },
    {
        "key": {
            "subgroup": "MALE",
            "year": 2016,
            "type": "Five Year ACGR"
        },
        "val": {
            "acgr": 0.416,
            "suppressed": 0
        }
    },
    {
        "key": {
            "subgroup": "Economy",
            "year": 2015,
            "type": "Five Year ACGR"
        },
        "val": {
            "acgr": 0.524,
            "suppressed": 0
        }
    },
    {
        "key": {
            "subgroup": "All",
            "year": 2015,
            "type": "Five Year ACGR"
        },
        "val": {
            "acgr": 0.52,
            "suppressed": 0
        }
    },
    {
        "key": {
            "subgroup": "BL7",
            "year": 2015,
            "type": "Five Year ACGR"
        },
        "val": {
            "acgr": 0.516,
            "suppressed": 0
        }
    },
    {
        "key": {
            "subgroup": "FEMALE",
            "year": 2015,
            "type": "Five Year ACGR"
        },
        "val": {
            "acgr": 0.568,
            "suppressed": 0
        }
    },
    {
        "key": {
            "subgroup": "MALE",
            "year": 2015,
            "type": "Five Year ACGR"
        },
        "val": {
            "acgr": 0.435,
            "suppressed": 0
        }
    },
    {
        "key": {
            "subgroup": "FEMALE",
            "year": 2016,
            "type": "Four Year ACGR"
        },
        "val": {
            "acgr": 0.42,
            "suppressed": 0
        }
    },
    {
        "key": {
            "subgroup": "MALE",
            "year": 2016,
            "type": "Four Year ACGR"
        },
        "val": {
            "acgr": 0.329,
            "suppressed": 0
        }
    },
    {
        "key": {
            "subgroup": "BL7",
            "year": 2016,
            "type": "Four Year ACGR"
        },
        "val": {
            "acgr": 0.385,
            "suppressed": 0
        }
    },
    {
        "key": {
            "subgroup": "Economy",
            "year": 2017,
            "type": "Five Year ACGR"
        },
        "val": {
            "acgr": 0.487,
            "suppressed": 0
        }
    },
    {
        "key": {
            "subgroup": "BL7",
            "year": 2017,
            "type": "Five Year ACGR"
        },
        "val": {
            "acgr": 0.494,
            "suppressed": 0
        }
    },
    {
        "key": {
            "subgroup": "All",
            "year": 2016,
            "type": "Four Year ACGR"
        },
        "val": {
            "acgr": 0.375,
            "suppressed": 0
        }
    },
    {
        "key": {
            "subgroup": "FEMALE",
            "year": 2017,
            "type": "Five Year ACGR"
        },
        "val": {
            "acgr": 0.519,
            "suppressed": 0
        }
    },
    {
        "key": {
            "subgroup": "MALE",
            "year": 2017,
            "type": "Five Year ACGR"
        },
        "val": {
            "acgr": 0.468,
            "suppressed": 0
        }
    },
    {
        "key": {
            "subgroup": "All",
            "year": 2017,
            "type": "Five Year ACGR"
        },
        "val": {
            "acgr": 0.494,
            "suppressed": 0
        }
    }
]

	}
}
