{
"timestamp": "Fri Feb 13 15:58:30 2015",
"org_type": "lea",
"org_name": "Maya Angelou PCS",
"org_code": "0133",
"exhibit": {
	"id": "sped_apr",
	"data":  
[
    {
        "key": {
            "year": 2012,
            "indicator": "1"
        },
        "val": {
            "val": 0.4118,
            "target": 0.85,
            "weight": 1,
            "target_dir": "up",
            "on_target": false
        }
    },
    {
        "key": {
            "year": 2012,
            "indicator": "10"
        },
        "val": {
            "val": 0,
            "target": 0,
            "weight": 1,
            "target_dir": "down",
            "on_target": true
        }
    },
    {
        "key": {
            "year": 2012,
            "indicator": "11"
        },
        "val": {
            "val": 0.78,
            "target": 1,
            "weight": 1,
            "target_dir": "up",
            "on_target": false
        }
    },
    {
        "key": {
            "year": 2012,
            "indicator": "12"
        },
        "val": {
            "val": null,
            "target": 1,
            "weight": 1,
            "target_dir": "up",
            "on_target": null
        }
    },
    {
        "key": {
            "year": 2012,
            "indicator": "13"
        },
        "val": {
            "val": 0.25,
            "target": 1,
            "weight": 1,
            "target_dir": "up",
            "on_target": false
        }
    },
    {
        "key": {
            "year": 2012,
            "indicator": "14_a"
        },
        "val": {
            "val": 0.5,
            "target": 0.27,
            "weight": 0.3333,
            "target_dir": "up",
            "on_target": true
        }
    },
    {
        "key": {
            "year": 2012,
            "indicator": "14_b"
        },
        "val": {
            "val": 0.5,
            "target": 0.51,
            "weight": 0.3333,
            "target_dir": "up",
            "on_target": false
        }
    },
    {
        "key": {
            "year": 2012,
            "indicator": "14_c"
        },
        "val": {
            "val": 0.5,
            "target": 0.64,
            "weight": 0.3333,
            "target_dir": "up",
            "on_target": false
        }
    },
    {
        "key": {
            "year": 2012,
            "indicator": "15"
        },
        "val": {
            "val": 0.89,
            "target": null,
            "weight": null,
            "target_dir": null,
            "on_target": null
        }
    },
    {
        "key": {
            "year": 2012,
            "indicator": "18"
        },
        "val": {
            "val": null,
            "target": null,
            "weight": null,
            "target_dir": null,
            "on_target": null
        }
    },
    {
        "key": {
            "year": 2012,
            "indicator": "19"
        },
        "val": {
            "val": null,
            "target": null,
            "weight": null,
            "target_dir": null,
            "on_target": null
        }
    },
    {
        "key": {
            "year": 2012,
            "indicator": "2"
        },
        "val": {
            "val": 0.06,
            "target": 0.06,
            "weight": 1,
            "target_dir": "down",
            "on_target": true
        }
    },
    {
        "key": {
            "year": 2012,
            "indicator": "20"
        },
        "val": {
            "val": null,
            "target": null,
            "weight": null,
            "target_dir": null,
            "on_target": null
        }
    },
    {
        "key": {
            "year": 2012,
            "indicator": "3a"
        },
        "val": {
            "val": 0,
            "target": 0.5,
            "weight": 0.3333,
            "target_dir": "up",
            "on_target": false
        }
    },
    {
        "key": {
            "year": 2012,
            "indicator": "3b_math"
        },
        "val": {
            "val": 0.97,
            "target": 0.95,
            "weight": 0.1667,
            "target_dir": "up",
            "on_target": true
        }
    },
    {
        "key": {
            "year": 2012,
            "indicator": "3b_reading"
        },
        "val": {
            "val": 0.97,
            "target": 0.95,
            "weight": 0.1667,
            "target_dir": "up",
            "on_target": true
        }
    },
    {
        "key": {
            "year": 2012,
            "indicator": "3c_elem_math"
        },
        "val": {
            "val": 0,
            "target": null,
            "weight": null,
            "target_dir": null,
            "on_target": null
        }
    },
    {
        "key": {
            "year": 2012,
            "indicator": "3c_elem_reading"
        },
        "val": {
            "val": 0,
            "target": null,
            "weight": null,
            "target_dir": null,
            "on_target": null
        }
    },
    {
        "key": {
            "year": 2012,
            "indicator": "3c_sec_math"
        },
        "val": {
            "val": 0.1176,
            "target": null,
            "weight": null,
            "target_dir": null,
            "on_target": null
        }
    },
    {
        "key": {
            "year": 2012,
            "indicator": "3c_sec_reading"
        },
        "val": {
            "val": 0.0392,
            "target": null,
            "weight": null,
            "target_dir": null,
            "on_target": null
        }
    },
    {
        "key": {
            "year": 2012,
            "indicator": "4a"
        },
        "val": {
            "val": 1,
            "target": 0,
            "weight": 0.5,
            "target_dir": "down",
            "on_target": false
        }
    },
    {
        "key": {
            "year": 2012,
            "indicator": "4b_a"
        },
        "val": {
            "val": 1,
            "target": 0,
            "weight": 0.25,
            "target_dir": "down",
            "on_target": false
        }
    },
    {
        "key": {
            "year": 2012,
            "indicator": "4b_b"
        },
        "val": {
            "val": 1,
            "target": 0,
            "weight": 0.25,
            "target_dir": "down",
            "on_target": false
        }
    },
    {
        "key": {
            "year": 2012,
            "indicator": "5a"
        },
        "val": {
            "val": 0.77,
            "target": 0.175,
            "weight": 0.3333,
            "target_dir": "up",
            "on_target": true
        }
    },
    {
        "key": {
            "year": 2012,
            "indicator": "5b"
        },
        "val": {
            "val": 0.09,
            "target": 0.15,
            "weight": 0.3333,
            "target_dir": "down",
            "on_target": true
        }
    },
    {
        "key": {
            "year": 2012,
            "indicator": "5c"
        },
        "val": {
            "val": 0.06,
            "target": 0.15,
            "weight": 0.3333,
            "target_dir": "down",
            "on_target": true
        }
    },
    {
        "key": {
            "year": 2012,
            "indicator": "6a"
        },
        "val": {
            "val": null,
            "target": 0.63,
            "weight": 0.5,
            "target_dir": "up",
            "on_target": null
        }
    },
    {
        "key": {
            "year": 2012,
            "indicator": "6b"
        },
        "val": {
            "val": null,
            "target": 0.15,
            "weight": 0.5,
            "target_dir": "down",
            "on_target": null
        }
    },
    {
        "key": {
            "year": 2012,
            "indicator": "7a_a"
        },
        "val": {
            "val": null,
            "target": 0.7,
            "weight": 0.1667,
            "target_dir": "up",
            "on_target": null
        }
    },
    {
        "key": {
            "year": 2012,
            "indicator": "7a_b"
        },
        "val": {
            "val": null,
            "target": 0.6,
            "weight": 0.1667,
            "target_dir": "up",
            "on_target": null
        }
    },
    {
        "key": {
            "year": 2012,
            "indicator": "7b_a"
        },
        "val": {
            "val": null,
            "target": 0.9,
            "weight": 0.1667,
            "target_dir": "up",
            "on_target": null
        }
    },
    {
        "key": {
            "year": 2012,
            "indicator": "7b_b"
        },
        "val": {
            "val": null,
            "target": 0.6,
            "weight": 0.1667,
            "target_dir": "up",
            "on_target": null
        }
    },
    {
        "key": {
            "year": 2012,
            "indicator": "7c_a"
        },
        "val": {
            "val": null,
            "target": 0.6,
            "weight": 0.1667,
            "target_dir": "up",
            "on_target": null
        }
    },
    {
        "key": {
            "year": 2012,
            "indicator": "7c_b"
        },
        "val": {
            "val": null,
            "target": 0.8,
            "weight": 0.1667,
            "target_dir": "up",
            "on_target": null
        }
    },
    {
        "key": {
            "year": 2012,
            "indicator": "8"
        },
        "val": {
            "val": null,
            "target": 0.75,
            "weight": 1,
            "target_dir": "up",
            "on_target": null
        }
    },
    {
        "key": {
            "year": 2012,
            "indicator": "9"
        },
        "val": {
            "val": 0,
            "target": 0,
            "weight": 1,
            "target_dir": "down",
            "on_target": true
        }
    }
]

	}
}
