{
"timestamp": "Wed Feb 18 15:25:20 2015",
"org_type": "school",
"org_name": "MARIE REED ES",
"org_code": "0284",
"exhibit": {
	"id": "amo_targets",
	"data":  
[
    {
        "key": {
            "subject": "Math",
            "grade": "all",
            "enrollment_status": "full_year",
            "subgroup": "ECONOMY",
            "year": 2014
        },
        "val": {
            "baseline": 0.4355,
            "target": 0.5766
        }
    },
    {
        "key": {
            "subject": "Math",
            "grade": "all",
            "enrollment_status": "full_year",
            "subgroup": "HI7",
            "year": 2014
        },
        "val": {
            "baseline": 0.4483,
            "target": 0.5862
        }
    },
    {
        "key": {
            "subject": "Math",
            "grade": "all",
            "enrollment_status": "full_year",
            "subgroup": "All",
            "year": 2014
        },
        "val": {
            "baseline": 0.4478,
            "target": 0.5858
        }
    },
    {
        "key": {
            "subject": "Math",
            "grade": "all",
            "enrollment_status": "full_year",
            "subgroup": "LEP",
            "year": 2014
        },
        "val": {
            "baseline": 0.4592,
            "target": 0.5944
        }
    },
    {
        "key": {
            "subject": "Reading",
            "grade": "all",
            "enrollment_status": "full_year",
            "subgroup": "ECONOMY",
            "year": 2014
        },
        "val": {
            "baseline": 0.3952,
            "target": 0.5464
        }
    },
    {
        "key": {
            "subject": "Reading",
            "grade": "all",
            "enrollment_status": "full_year",
            "subgroup": "HI7",
            "year": 2014
        },
        "val": {
            "baseline": 0.4023,
            "target": 0.5517
        }
    },
    {
        "key": {
            "subject": "Reading",
            "grade": "all",
            "enrollment_status": "full_year",
            "subgroup": "All",
            "year": 2014
        },
        "val": {
            "baseline": 0.4104,
            "target": 0.5578
        }
    },
    {
        "key": {
            "subject": "Reading",
            "grade": "all",
            "enrollment_status": "full_year",
            "subgroup": "LEP",
            "year": 2014
        },
        "val": {
            "baseline": 0.4082,
            "target": 0.5561
        }
    }
]

	}
}
