{
"timestamp": "Wed Feb 18 15:25:25 2015",
"org_type": "school",
"org_name": "BRUCE MONROE ES AT PARK VIEW",
"org_code": "0296",
"exhibit": {
	"id": "amo_targets",
	"data":  
[
    {
        "key": {
            "subject": "Math",
            "grade": "all",
            "enrollment_status": "full_year",
            "subgroup": "ECONOMY",
            "year": 2014
        },
        "val": {
            "baseline": 0.4286,
            "target": 0.5714
        }
    },
    {
        "key": {
            "subject": "Math",
            "grade": "all",
            "enrollment_status": "full_year",
            "subgroup": "HI7",
            "year": 2014
        },
        "val": {
            "baseline": 0.5765,
            "target": 0.6824
        }
    },
    {
        "key": {
            "subject": "Math",
            "grade": "all",
            "enrollment_status": "full_year",
            "subgroup": "All",
            "year": 2014
        },
        "val": {
            "baseline": 0.4304,
            "target": 0.5728
        }
    },
    {
        "key": {
            "subject": "Math",
            "grade": "all",
            "enrollment_status": "full_year",
            "subgroup": "BL7",
            "year": 2014
        },
        "val": {
            "baseline": 0.2535,
            "target": 0.4401
        }
    },
    {
        "key": {
            "subject": "Math",
            "grade": "all",
            "enrollment_status": "full_year",
            "subgroup": "LEP",
            "year": 2014
        },
        "val": {
            "baseline": 0.5111,
            "target": 0.6333
        }
    },
    {
        "key": {
            "subject": "Reading",
            "grade": "all",
            "enrollment_status": "full_year",
            "subgroup": "ECONOMY",
            "year": 2014
        },
        "val": {
            "baseline": 0.3071,
            "target": 0.4804
        }
    },
    {
        "key": {
            "subject": "Reading",
            "grade": "all",
            "enrollment_status": "full_year",
            "subgroup": "HI7",
            "year": 2014
        },
        "val": {
            "baseline": 0.3059,
            "target": 0.4794
        }
    },
    {
        "key": {
            "subject": "Reading",
            "grade": "all",
            "enrollment_status": "full_year",
            "subgroup": "All",
            "year": 2014
        },
        "val": {
            "baseline": 0.2975,
            "target": 0.4731
        }
    },
    {
        "key": {
            "subject": "Reading",
            "grade": "all",
            "enrollment_status": "full_year",
            "subgroup": "BL7",
            "year": 2014
        },
        "val": {
            "baseline": 0.2817,
            "target": 0.4613
        }
    },
    {
        "key": {
            "subject": "Reading",
            "grade": "all",
            "enrollment_status": "full_year",
            "subgroup": "LEP",
            "year": 2014
        },
        "val": {
            "baseline": 0.2667,
            "target": 0.45
        }
    }
]

	}
}
