{
"timestamp": "Mon Nov 10 15:27:54 2014",
"org_type": "school",
"org_name": "",
"org_code": "1117",
"exhibit": {
	"id": "suspensions",
	"data":  
[{"key":{"year":2013,"subgroup":"All"},"val":{"suspended_1":0.03,"suspended_11":0,"state_suspended_1":0.06,"state_suspended_11":0}},{"key":{"year":2013,"subgroup":"AS7"},"val":{"suspended_1":0,"suspended_11":0,"state_suspended_1":0.01,"state_suspended_11":0}},{"key":{"year":2013,"subgroup":"BL7"},"val":{"suspended_1":0.05,"suspended_11":0,"state_suspended_1":0.08,"state_suspended_11":0}},{"key":{"year":2013,"subgroup":"Economy"},"val":{"suspended_1":0.05,"suspended_11":0,"state_suspended_1":0.08,"state_suspended_11":0}},{"key":{"year":2013,"subgroup":"HI7"},"val":{"suspended_1":0.07,"suspended_11":0,"state_suspended_1":0.02,"state_suspended_11":0}},{"key":{"year":2013,"subgroup":"LEP"},"val":{"suspended_1":0,"suspended_11":0,"state_suspended_1":0.02,"state_suspended_11":0}},{"key":{"year":2013,"subgroup":"MU7"},"val":{"suspended_1":0.03,"suspended_11":0,"state_suspended_1":0.03,"state_suspended_11":0}},{"key":{"year":2013,"subgroup":"SPED"},"val":{"suspended_1":0.13,"suspended_11":0,"state_suspended_1":0.11,"state_suspended_11":0}},{"key":{"year":2013,"subgroup":"WH7"},"val":{"suspended_1":0.01,"suspended_11":0,"state_suspended_1":0,"state_suspended_11":0}},{"key":{"year":2014,"subgroup":"All"},"val":{"suspended_1":0.0274,"suspended_11":0,"state_suspended_1":0.0774,"state_suspended_11":0.0007}},{"key":{"year":2014,"subgroup":"AS7"},"val":{"suspended_1":0.02,"suspended_11":0,"state_suspended_1":0.0154,"state_suspended_11":0}},{"key":{"year":2014,"subgroup":"BL7"},"val":{"suspended_1":0.0433,"suspended_11":0,"state_suspended_1":0.1041,"state_suspended_11":0.001}},{"key":{"year":2014,"subgroup":"Economy"},"val":{"suspended_1":0.0769,"suspended_11":0,"state_suspended_1":0.0931,"state_suspended_11":0.0009}},{"key":{"year":2014,"subgroup":"FEMALE"},"val":{"suspended_1":0.0115,"suspended_11":0,"state_suspended_1":0.0519,"state_suspended_11":0.0004}},{"key":{"year":2014,"subgroup":"HI7"},"val":{"suspended_1":0.0313,"suspended_11":0,"state_suspended_1":0.0608,"state_suspended_11":0}},{"key":{"year":2014,"subgroup":"LEP"},"val":{"suspended_1":0,"suspended_11":0,"state_suspended_1":0.0304,"state_suspended_11":0}},{"key":{"year":2014,"subgroup":"MALE"},"val":{"suspended_1":0.0438,"suspended_11":0,"state_suspended_1":0.1025,"state_suspended_11":0.001}},{"key":{"year":2014,"subgroup":"MU7"},"val":{"suspended_1":0.0241,"suspended_11":0,"state_suspended_1":0.0238,"state_suspended_11":0}},{"key":{"year":2014,"subgroup":"SPED"},"val":{"suspended_1":0,"suspended_11":0,"state_suspended_1":0.1413,"state_suspended_11":0.0014}},{"key":{"year":2014,"subgroup":"WH7"},"val":{"suspended_1":0.0073,"suspended_11":0,"state_suspended_1":0.0057,"state_suspended_11":0}}]
	}
}
